{
  "meta": {
    "newWordsMustBeUniqueUntilExhausted": true,
    "reviewFormat": "guided_cloze_with_grammar_chunking",
    "sourceScope": "台灣普遍認定國中必會1000單",
    "updatedAt": "2026-05-14T11:00:58.200565Z"
  },
  "words": {
    "adventure": {
      "first_seen": "2025-02-23",
      "last_seen": "2025-02-23",
      "meanings": [
        "冒險"
      ]
    },
    "afraid": {
      "example_sentence": "I am afraid of the dark.",
      "first_seen": "2026-04-15",
      "last_seen": "2026-04-15",
      "meanings": [
        "害怕的；擔心的"
      ],
      "translation": "我怕黑。"
    },
    "agree": {
      "example_sentence": "I agree with your idea.",
      "first_seen": "2026-04-25",
      "last_seen": "2026-04-25",
      "meanings": [
        "同意"
      ],
      "pos": "v",
      "translation": "我同意你的想法。"
    },
    "although": {
      "first_seen": "2026-05-14",
      "last_seen": "2026-05-14",
      "meanings": [
        "雖然；儘管"
      ],
      "pos": "conj",
      "example_sentence": "Although it was raining, we still went outside.",
      "translation": "雖然在下雨，我們還是出門了。"
    },
    "always": {
      "example_sentence": "She always eats breakfast.",
      "first_seen": "2026-04-28",
      "last_seen": "2026-04-28",
      "meanings": [
        "總是；一直"
      ],
      "pos": "adv",
      "translation": "她總是會吃早餐。"
    },
    "arrive": {
      "example_sentence": "We will arrive at school before eight.",
      "first_seen": "2026-03-08",
      "last_seen": "2026-03-08",
      "meanings": [
        "到達"
      ],
      "translation": "我們會在八點前到達學校。"
    },
    "balcony": {
      "example_sentence": "She is standing on the balcony.",
      "first_seen": "2026-04-05",
      "last_seen": "2026-04-05",
      "meanings": [
        "陽台"
      ],
      "translation": "她正站在陽台上。"
    },
    "behind": {
      "example_sentence": "The cat is behind the chair.",
      "first_seen": "2026-05-02",
      "last_seen": "2026-05-02",
      "meanings": [
        "在…後面；在後方"
      ],
      "pos": [
        "prep",
        "adv"
      ],
      "translation": "那隻貓在椅子後面。"
    },
    "believe": {
      "example_sentence": "I believe you can do it.",
      "first_seen": "2026-04-21",
      "last_seen": "2026-04-21",
      "meanings": [
        "相信；信任"
      ],
      "translation": "我相信你做得到。"
    },
    "belong": {
      "example_sentence": "This pencil belongs to you.",
      "first_seen": "2026-04-09",
      "last_seen": "2026-04-09",
      "meanings": [
        "屬於"
      ],
      "translation": "這枝鉛筆是你的。"
    },
    "between": {
      "example_sentence": "The ball is between the two chairs.",
      "first_seen": "2026-05-01",
      "last_seen": "2026-05-01",
      "meanings": [
        "在…之間"
      ],
      "pos": "prep",
      "translation": "球在兩張椅子中間。"
    },
    "blow": {
      "example_sentence": "Please blow on the soup. It is hot.",
      "first_seen": "2026-04-14",
      "last_seen": "2026-04-14",
      "meanings": [
        "吹；吹氣；吹風"
      ],
      "translation": "請對湯吹一吹，它很燙。"
    },
    "borrow": {
      "example_sentence": "Can I borrow your pencil?",
      "first_seen": "2026-03-04",
      "last_seen": "2026-03-04",
      "meanings": [
        "借"
      ],
      "translation": "我可以借你的鉛筆嗎？"
    },
    "bottle": {
      "example_sentence": "Please put some water in the bottle.",
      "first_seen": "2026-04-23",
      "last_seen": "2026-04-23",
      "meanings": [
        "瓶子"
      ],
      "translation": "請把一些水裝進瓶子裡。"
    },
    "box": {
      "example_sentence": "Put the toys in the box.",
      "first_seen": "2026-05-12",
      "last_seen": "2026-05-12",
      "meanings": [
        "盒子；箱子"
      ],
      "pos": "n",
      "translation": "把玩具放進盒子裡。"
    },
    "brave": {
      "example_sentence": "The brave girl spoke in front of the class.",
      "first_seen": "2026-03-04",
      "last_seen": "2026-03-04",
      "meanings": [
        "勇敢的"
      ],
      "translation": "那位勇敢的女孩在全班前面發言。"
    },
    "bridge": {
      "first_seen": "2026-05-14",
      "last_seen": "2026-05-14",
      "meanings": [
        "橋；橋樑"
      ],
      "pos": "n",
      "example_sentence": "We walked across the bridge.",
      "translation": "我們走過那座橋。"
    },
    "build": {
      "example_sentence": "We will build a sandcastle at the beach.",
      "first_seen": "2026-05-04",
      "last_seen": "2026-05-04",
      "meanings": [
        "建造；建立"
      ],
      "pos": "v",
      "translation": "我們要在海灘堆一座沙堡。"
    },
    "camera": {
      "example_sentence": "I took a photo with my camera.",
      "first_seen": "2026-04-07",
      "last_seen": "2026-04-07",
      "meanings": [
        "相機；攝影機"
      ],
      "translation": "我用我的相機拍了一張照片。"
    },
    "careful": {
      "example_sentence": "Be careful when you cross the street.",
      "first_seen": "2026-03-03",
      "last_seen": "2026-03-03",
      "meanings": [
        "小心的；謹慎的"
      ],
      "translation": "過馬路時要小心。"
    },
    "cat": {
      "example_sentence": "The cat is sleeping.",
      "first_seen": "2026-05-02",
      "last_seen": "2026-05-02",
      "meanings": [
        "貓"
      ],
      "pos": "n",
      "translation": "那隻貓在睡覺。"
    },
    "catch": {
      "example_sentence": "I can catch the ball.",
      "first_seen": "2026-04-25",
      "last_seen": "2026-04-25",
      "meanings": [
        "接住；抓住"
      ],
      "pos": "v",
      "translation": "我可以接住球。"
    },
    "child": {
      "example_sentence": "The child is playing in the park.",
      "first_seen": "2026-04-04",
      "last_seen": "2026-04-04",
      "meanings": [
        "小孩；孩子"
      ],
      "translation": "那個孩子正在公園玩。"
    },
    "choose": {
      "example_sentence": "Please choose one book.",
      "first_seen": "2026-04-06",
      "last_seen": "2026-04-06",
      "meanings": [
        "選擇；挑選"
      ],
      "translation": "請選一本書。"
    },
    "classmate": {
      "example_sentence": "My classmate sits next to me.",
      "first_seen": "2026-04-09",
      "last_seen": "2026-04-09",
      "meanings": [
        "同學；同班同學"
      ],
      "translation": "我的同學坐在我旁邊。"
    },
    "clearly": {
      "example_sentence": "Please speak clearly.",
      "first_seen": "2026-04-02",
      "last_seen": "2026-04-02",
      "meanings": [
        "清楚地；明確地"
      ],
      "translation": "請講清楚一點。"
    },
    "clever": {
      "example_sentence": "The clever boy solved the puzzle quickly.",
      "first_seen": "2026-03-06",
      "last_seen": "2026-03-06",
      "meanings": [
        "聰明的"
      ],
      "translation": "那個聰明的男孩很快解開了謎題。"
    },
    "close": {
      "example_sentence": "Please close the door.",
      "first_seen": "2026-04-07",
      "last_seen": "2026-04-07",
      "meanings": [
        "關上；關閉"
      ],
      "translation": "請把門關上。"
    },
    "cloud": {
      "example_sentence": "That cloud looks like a rabbit.",
      "first_seen": "2026-03-22",
      "last_seen": "2026-03-22",
      "meanings": [
        "雲"
      ],
      "translation": "那朵雲看起來像一隻兔子。"
    },
    "coffee": {
      "example_sentence": "My dad drinks coffee in the morning.",
      "first_seen": "2026-04-28",
      "last_seen": "2026-04-28",
      "meanings": [
        "咖啡"
      ],
      "pos": "n",
      "translation": "我爸爸早上會喝咖啡。"
    },
    "comfortable": {
      "example_sentence": "This chair is comfortable.",
      "first_seen": "2026-05-05",
      "last_seen": "2026-05-05",
      "meanings": [
        "舒服的；舒適的"
      ],
      "pos": "adj",
      "translation": "這張椅子很舒服。"
    },
    "contest": {
      "example_sentence": "She won the singing contest.",
      "first_seen": "2026-03-24",
      "last_seen": "2026-03-24",
      "meanings": [
        "比賽"
      ],
      "translation": "她贏得了歌唱比賽。"
    },
    "conversation": {
      "example_sentence": "We had a long conversation after class.",
      "first_seen": "2026-04-14",
      "last_seen": "2026-04-14",
      "meanings": [
        "對話；談話"
      ],
      "translation": "下課後我們聊了很久。"
    },
    "correctly": {
      "example_sentence": "Please write your name correctly.",
      "first_seen": "2026-04-28",
      "last_seen": "2026-04-28",
      "meanings": [
        "正確地"
      ],
      "pos": "adv",
      "translation": "請把你的名字寫正確。"
    },
    "crayon": {
      "example_sentence": "My child drew a sun with a yellow crayon.",
      "first_seen": "2026-05-03",
      "last_seen": "2026-05-03",
      "meanings": [
        "蠟筆"
      ],
      "pos": "n",
      "translation": "我的孩子用黃色蠟筆畫了一個太陽。"
    },
    "curious": {
      "first_seen": "2025-02-23",
      "last_seen": "2025-02-23",
      "meanings": [
        "好奇的"
      ]
    },
    "dangerous": {
      "first_seen": "2025-02-23",
      "last_seen": "2025-02-23",
      "meanings": [
        "危險的"
      ]
    },
    "dark": {
      "example_sentence": "It is dark outside.",
      "first_seen": "2026-04-06",
      "last_seen": "2026-04-06",
      "meanings": [
        "黑暗的；暗的"
      ],
      "translation": "外面很暗。"
    },
    "desk": {
      "example_sentence": "Please put your books on the desk.",
      "first_seen": "2026-04-19",
      "last_seen": "2026-04-19",
      "meanings": [
        "書桌；桌子"
      ],
      "translation": "請把你的書放在桌上。"
    },
    "discover": {
      "first_seen": "2026-02-24",
      "last_seen": "2026-02-24",
      "meanings": [
        "發現"
      ]
    },
    "divide": {
      "example_sentence": "Divide 12 by 3.",
      "first_seen": "2026-03-29",
      "last_seen": "2026-03-29",
      "meanings": [
        "分開；分成；除以"
      ],
      "translation": "把 12 除以 3。"
    },
    "doctor": {
      "example_sentence": "The doctor helps sick people.",
      "first_seen": "2026-05-08",
      "last_seen": "2026-05-08",
      "meanings": [
        "醫生"
      ],
      "pos": "n",
      "translation": "醫生會幫助生病的人。"
    },
    "dragon": {
      "example_sentence": "The dragon in the story is very strong.",
      "first_seen": "2026-04-20",
      "last_seen": "2026-04-20",
      "meanings": [
        "龍"
      ],
      "translation": "故事裡的龍很強。"
    },
    "drop": {
      "example_sentence": "I dropped my pencil on the floor.",
      "first_seen": "2026-05-07",
      "last_seen": "2026-05-07",
      "meanings": [
        "掉下來；掉落",
        "放下；放開（手上的東西）"
      ],
      "pos": "v",
      "translation": "我把鉛筆掉到地上了。"
    },
    "early": {
      "example_sentence": "She gets up early every morning.",
      "first_seen": "2026-03-23",
      "last_seen": "2026-03-23",
      "meanings": [
        "早地；提早"
      ],
      "translation": "她每天早上都很早起床。"
    },
    "enemy": {
      "example_sentence": "He is not my enemy.",
      "first_seen": "2026-04-15",
      "last_seen": "2026-04-15",
      "meanings": [
        "敵人"
      ],
      "translation": "他不是我的敵人。"
    },
    "every": {
      "example_sentence": "I brush my teeth every night.",
      "first_seen": "2026-04-29",
      "last_seen": "2026-04-29",
      "meanings": [
        "每一個；每"
      ],
      "pos": "det",
      "translation": "我每天晚上都刷牙。"
    },
    "everywhere": {
      "example_sentence": "I looked everywhere for my pencil.",
      "first_seen": "2026-04-08",
      "last_seen": "2026-04-08",
      "meanings": [
        "到處；各處"
      ],
      "translation": "我到處找我的鉛筆。"
    },
    "excellent": {
      "first_seen": "2026-02-24",
      "last_seen": "2026-02-24",
      "meanings": [
        "極好的、優秀的"
      ]
    },
    "excited": {
      "example_sentence": "She is excited about the school trip.",
      "first_seen": "2026-03-03",
      "last_seen": "2026-03-03",
      "meanings": [
        "興奮的"
      ],
      "translation": "她對學校旅行感到很興奮。"
    },
    "fan": {
      "example_sentence": "Please turn on the fan.",
      "first_seen": "2026-04-11",
      "last_seen": "2026-04-11",
      "meanings": [
        "風扇；電風扇"
      ],
      "translation": "請把電風扇打開。"
    },
    "father": {
      "example_sentence": "My father is at work.",
      "first_seen": "2026-04-30",
      "last_seen": "2026-04-30",
      "meanings": [
        "爸爸；父親"
      ],
      "pos": "n",
      "translation": "我爸爸在上班。"
    },
    "feel": {
      "example_sentence": "I feel tired after school.",
      "first_seen": "2026-03-26",
      "last_seen": "2026-03-26",
      "meanings": [
        "感覺；覺得"
      ],
      "translation": "放學後我覺得很累。"
    },
    "first": {
      "example_sentence": "I was first in line.",
      "first_seen": "2026-05-05",
      "last_seen": "2026-05-05",
      "meanings": [
        "第一（的）；最先"
      ],
      "pos": [
        "adj",
        "adv"
      ],
      "translation": "我排在隊伍最前面。"
    },
    "forest": {
      "example_sentence": "We walked through the forest after lunch.",
      "first_seen": "2026-03-08",
      "last_seen": "2026-03-08",
      "meanings": [
        "森林"
      ],
      "translation": "午餐後我們穿過森林散步。"
    },
    "forward": {
      "example_sentence": "Please move forward.",
      "first_seen": "2026-04-04",
      "last_seen": "2026-04-04",
      "meanings": [
        "向前；前方的"
      ],
      "translation": "請往前移一點。"
    },
    "free": {
      "example_sentence": "This app is free.",
      "first_seen": "2026-05-08",
      "last_seen": "2026-05-08",
      "meanings": [
        "免費的",
        "自由的",
        "空閒的"
      ],
      "pos": "adj",
      "translation": "這個 App 是免費的。"
    },
    "freeze": {
      "example_sentence": "Water can freeze in winter.",
      "first_seen": "2026-05-06",
      "last_seen": "2026-05-06",
      "meanings": [
        "結冰；冷凍；凍住"
      ],
      "pos": "v",
      "translation": "水在冬天會結冰。"
    },
    "friendly": {
      "example_sentence": "Our new classmate is very friendly.",
      "first_seen": "2026-03-02",
      "last_seen": "2026-03-02",
      "meanings": [
        "友善的；親切的"
      ],
      "translation": "我們的新同學非常友善。"
    },
    "fun": {
      "example_sentence": "The game is fun.",
      "first_seen": "2026-04-14",
      "last_seen": "2026-04-14",
      "meanings": [
        "樂趣；好玩"
      ],
      "translation": "這個遊戲很好玩。"
    },
    "gentle": {
      "example_sentence": "Be gentle with the baby.",
      "first_seen": "2026-02-28",
      "last_seen": "2026-02-28",
      "meanings": [
        "溫柔的；輕柔的"
      ],
      "translation": "對寶寶要溫柔一點。"
    },
    "gift": {
      "example_sentence": "I got a gift from my friend.",
      "first_seen": "2026-04-29",
      "last_seen": "2026-04-29",
      "meanings": [
        "禮物"
      ],
      "pos": "n",
      "translation": "我收到朋友送的禮物。"
    },
    "giggle": {
      "example_sentence": "The kids giggle when they hear a funny joke.",
      "first_seen": "2026-03-05",
      "last_seen": "2026-03-05",
      "meanings": [
        "咯咯笑；傻笑"
      ],
      "translation": "孩子們聽到好笑的笑話會咯咯笑。"
    },
    "glass": {
      "example_sentence": "There is a glass of milk on the table.",
      "first_seen": "2026-03-25",
      "last_seen": "2026-03-25",
      "meanings": [
        "玻璃杯；玻璃"
      ],
      "translation": "桌上有一杯牛奶。"
    },
    "glove": {
      "example_sentence": "This glove is too big for my hand.",
      "first_seen": "2026-03-25",
      "last_seen": "2026-03-25",
      "meanings": [
        "手套"
      ],
      "translation": "這隻手套對我的手來說太大了。"
    },
    "gray": {
      "example_sentence": "The sky is gray today.",
      "first_seen": "2026-05-07",
      "last_seen": "2026-05-07",
      "meanings": [
        "灰色的"
      ],
      "pos": "adj",
      "translation": "今天的天空是灰灰的。"
    },
    "guess": {
      "first_seen": "2026-05-13",
      "last_seen": "2026-05-13",
      "meanings": [
        "猜；猜測"
      ],
      "example_sentence": "Can you guess the answer?",
      "translation": "你猜得出答案嗎？",
      "pos": [
        "v",
        "n"
      ]
    },
    "happy": {
      "example_sentence": "I am happy today.",
      "first_seen": "2026-03-26",
      "last_seen": "2026-03-26",
      "meanings": [
        "開心的；快樂的"
      ],
      "translation": "我今天很開心。"
    },
    "hate": {
      "example_sentence": "I hate spiders.",
      "first_seen": "2026-05-04",
      "last_seen": "2026-05-04",
      "meanings": [
        "討厭；憎恨"
      ],
      "pos": "v",
      "translation": "我討厭蜘蛛。"
    },
    "heavy": {
      "example_sentence": "This bag is heavy.",
      "first_seen": "2026-04-30",
      "last_seen": "2026-04-30",
      "meanings": [
        "重的；沉的"
      ],
      "pos": "adj",
      "translation": "這個袋子很重。"
    },
    "help": {
      "example_sentence": "Can you help me with my homework?",
      "first_seen": "2026-05-07",
      "last_seen": "2026-05-07",
      "meanings": [
        "幫助；協助"
      ],
      "pos": [
        "v",
        "n"
      ],
      "translation": "你可以幫我寫作業嗎？"
    },
    "hide": {
      "example_sentence": "Don't hide your feelings.",
      "first_seen": "2026-04-02",
      "last_seen": "2026-04-02",
      "meanings": [
        "躲起來；藏起來"
      ],
      "translation": "不要把你的感覺藏起來。"
    },
    "hippo": {
      "example_sentence": "I saw a hippo at the zoo.",
      "first_seen": "2026-04-03",
      "last_seen": "2026-04-03",
      "meanings": [
        "河馬"
      ],
      "translation": "我在動物園看到一隻河馬。"
    },
    "hole": {
      "example_sentence": "There is a big hole in the ground.",
      "first_seen": "2026-04-19",
      "last_seen": "2026-04-19",
      "meanings": [
        "洞；孔洞"
      ],
      "translation": "地上有一個大洞。"
    },
    "homework": {
      "example_sentence": "I finished my homework after dinner.",
      "first_seen": "2026-04-13",
      "last_seen": "2026-04-13",
      "meanings": [
        "作業；功課"
      ],
      "translation": "我晚餐後把作業寫完了。"
    },
    "hospital": {
      "example_sentence": "He is in the hospital.",
      "first_seen": "2026-04-12",
      "last_seen": "2026-04-12",
      "meanings": [
        "醫院"
      ],
      "translation": "他在醫院裡。"
    },
    "hotel": {
      "example_sentence": "We stayed in a nice hotel last night.",
      "first_seen": "2026-04-19",
      "last_seen": "2026-04-19",
      "meanings": [
        "旅館；飯店"
      ],
      "translation": "我們昨晚住在一間不錯的飯店。"
    },
    "hungry": {
      "example_sentence": "I am hungry. Can I have a sandwich?",
      "first_seen": "2026-03-01",
      "last_seen": "2026-03-01",
      "meanings": [
        "肚子餓的"
      ],
      "translation": "我肚子餓了。我可以吃一個三明治嗎？"
    },
    "idea": {
      "example_sentence": "That's a great idea!",
      "first_seen": "2026-04-07",
      "last_seen": "2026-04-07",
      "meanings": [
        "點子；想法"
      ],
      "translation": "那是個好主意！"
    },
    "important": {
      "first_seen": "2025-02-23",
      "last_seen": "2025-02-23",
      "meanings": [
        "重要的"
      ]
    },
    "improve": {
      "example_sentence": "Reading every day helps improve your English.",
      "first_seen": "2026-02-28",
      "last_seen": "2026-02-28",
      "meanings": [
        "改善；進步"
      ],
      "translation": "每天閱讀有助於提升你的英文。"
    },
    "inside": {
      "example_sentence": "Please put the toy inside the box.",
      "first_seen": "2026-05-01",
      "last_seen": "2026-05-01",
      "meanings": [
        "在…裡面"
      ],
      "pos": [
        "prep",
        "adv"
      ],
      "translation": "請把玩具放進盒子裡。"
    },
    "invite": {
      "example_sentence": "I want to invite my friend to the party.",
      "first_seen": "2026-03-07",
      "last_seen": "2026-03-07",
      "meanings": [
        "邀請"
      ],
      "translation": "我想邀請我的朋友來參加派對。"
    },
    "joke": {
      "example_sentence": "That joke is funny.",
      "first_seen": "2026-03-28",
      "last_seen": "2026-03-28",
      "meanings": [
        "笑話",
        "開玩笑"
      ],
      "translation": "那個笑話很好笑。"
    },
    "journey": {
      "example_sentence": "Our journey to the museum was fun.",
      "first_seen": "2026-03-05",
      "last_seen": "2026-03-05",
      "meanings": [
        "旅程；一段路途"
      ],
      "translation": "我們去博物館的旅程很有趣。"
    },
    "jump": {
      "example_sentence": "The cat can jump very high.",
      "first_seen": "2026-04-17",
      "last_seen": "2026-04-17",
      "meanings": [
        "跳；跳躍"
      ],
      "translation": "那隻貓可以跳得很高。"
    },
    "kick": {
      "example_sentence": "Don't kick the ball inside the classroom.",
      "first_seen": "2026-03-31",
      "last_seen": "2026-03-31",
      "meanings": [
        "踢；踢一下"
      ],
      "translation": "不要在教室裡踢球。"
    },
    "kill": {
      "example_sentence": "This soap can kill germs.",
      "first_seen": "2026-04-06",
      "last_seen": "2026-04-06",
      "meanings": [
        "殺死；消滅（細菌等）"
      ],
      "translation": "這種肥皂可以殺死細菌。"
    },
    "kind": {
      "example_sentence": "My teacher is kind to everyone.",
      "first_seen": "2026-05-12",
      "last_seen": "2026-05-12",
      "meanings": [
        "親切的；善良的"
      ],
      "pos": "adj",
      "translation": "我的老師對每個人都很親切。"
    },
    "kiss": {
      "example_sentence": "Give Mom a kiss.",
      "first_seen": "2026-04-11",
      "last_seen": "2026-04-11",
      "meanings": [
        "親吻；吻"
      ],
      "translation": "給媽媽一個吻。"
    },
    "kitchen": {
      "example_sentence": "My mother is cooking in the kitchen.",
      "first_seen": "2026-03-23",
      "last_seen": "2026-03-23",
      "meanings": [
        "廚房"
      ],
      "translation": "我媽媽正在廚房煮飯。"
    },
    "lake": {
      "example_sentence": "We saw ducks on the lake.",
      "first_seen": "2026-03-24",
      "last_seen": "2026-03-24",
      "meanings": [
        "湖；湖泊"
      ],
      "translation": "我們看到湖上有鴨子。"
    },
    "land": {
      "example_sentence": "The plane will land soon.",
      "first_seen": "2026-04-09",
      "last_seen": "2026-04-09",
      "meanings": [
        "降落；著陸"
      ],
      "translation": "飛機很快就會降落。"
    },
    "leave": {
      "example_sentence": "I have to leave now.",
      "first_seen": "2026-04-03",
      "last_seen": "2026-04-03",
      "meanings": [
        "離開；離去"
      ],
      "translation": "我現在得離開了。"
    },
    "lend": {
      "example_sentence": "Can you lend your ruler to me?",
      "first_seen": "2026-04-17",
      "last_seen": "2026-04-17",
      "meanings": [
        "借出；借給"
      ],
      "translation": "你可以把你的尺借給我嗎？"
    },
    "library": {
      "example_sentence": "We read books in the library.",
      "first_seen": "2026-05-10",
      "last_seen": "2026-05-10",
      "meanings": [
        "圖書館"
      ],
      "pos": "n",
      "translation": "我們在圖書館看書。"
    },
    "live": {
      "example_sentence": "We live near the school.",
      "first_seen": "2026-05-11",
      "last_seen": "2026-05-11",
      "meanings": [
        "住；居住",
        "活著；生活"
      ],
      "pos": [
        "v"
      ],
      "translation": "我們住在學校附近。"
    },
    "look": {
      "example_sentence": "Look at the picture.",
      "first_seen": "2026-04-26",
      "last_seen": "2026-04-26",
      "meanings": [
        "看；看一看",
        "看起來"
      ],
      "pos": [
        "v",
        "n"
      ],
      "translation": "看看這張圖。"
    },
    "love": {
      "example_sentence": "I love my family.",
      "first_seen": "2026-05-09",
      "last_seen": "2026-05-09",
      "meanings": [
        "愛；喜愛"
      ],
      "pos": [
        "v",
        "n"
      ],
      "translation": "我愛我的家人。"
    },
    "luck": {
      "example_sentence": "Good luck on your test!",
      "first_seen": "2026-04-12",
      "last_seen": "2026-04-12",
      "meanings": [
        "運氣；好運"
      ],
      "translation": "考試加油，祝你好運！"
    },
    "mean": {
      "example_sentence": "What does this word mean?",
      "first_seen": "2026-04-12",
      "last_seen": "2026-04-12",
      "meanings": [
        "意思是；表示"
      ],
      "translation": "這個字是什麼意思？"
    },
    "meet": {
      "example_sentence": "I will meet my friend after school.",
      "first_seen": "2026-04-22",
      "last_seen": "2026-04-22",
      "meanings": [
        "遇見；見面"
      ],
      "translation": "我放學後要去見我的朋友。"
    },
    "mirror": {
      "example_sentence": "I looked at myself in the mirror.",
      "first_seen": "2026-03-07",
      "last_seen": "2026-03-07",
      "meanings": [
        "鏡子"
      ],
      "translation": "我在鏡子裡看著自己。"
    },
    "moon": {
      "example_sentence": "The moon is bright tonight.",
      "first_seen": "2026-03-27",
      "last_seen": "2026-03-27",
      "meanings": [
        "月亮"
      ],
      "translation": "今晚月亮很亮。"
    },
    "mouth": {
      "first_seen": "2026-05-13",
      "last_seen": "2026-05-13",
      "meanings": [
        "嘴巴；口"
      ],
      "example_sentence": "Open your mouth, please.",
      "translation": "請把嘴巴張開。",
      "pos": "n"
    },
    "nature": {
      "example_sentence": "I love nature.",
      "first_seen": "2026-05-10",
      "last_seen": "2026-05-10",
      "meanings": [
        "大自然"
      ],
      "pos": "n",
      "translation": "我喜歡大自然。"
    },
    "news": {
      "example_sentence": "I watched the news with my dad.",
      "first_seen": "2026-04-08",
      "last_seen": "2026-04-08",
      "meanings": [
        "新聞；消息"
      ],
      "translation": "我跟爸爸一起看新聞。"
    },
    "nice": {
      "example_sentence": "She is a nice teacher.",
      "first_seen": "2026-04-22",
      "last_seen": "2026-04-22",
      "meanings": [
        "不錯的；親切的"
      ],
      "translation": "她是一位很親切的老師。"
    },
    "noisy": {
      "example_sentence": "The classroom is noisy during break time.",
      "first_seen": "2026-03-08",
      "last_seen": "2026-03-08",
      "meanings": [
        "吵鬧的"
      ],
      "translation": "下課時間教室很吵鬧。"
    },
    "nose": {
      "example_sentence": "My nose is cold.",
      "first_seen": "2026-04-05",
      "last_seen": "2026-04-05",
      "meanings": [
        "鼻子"
      ],
      "translation": "我的鼻子冰冰的。"
    },
    "now": {
      "example_sentence": "I have to go now.",
      "first_seen": "2026-04-13",
      "last_seen": "2026-04-13",
      "meanings": [
        "現在"
      ],
      "translation": "我現在得走了。"
    },
    "onion": {
      "example_sentence": "I cut an onion for dinner.",
      "first_seen": "2026-03-27",
      "last_seen": "2026-03-27",
      "meanings": [
        "洋蔥"
      ],
      "translation": "我為晚餐切了一顆洋蔥。"
    },
    "order": {
      "first_seen": "2026-05-13",
      "last_seen": "2026-05-13",
      "meanings": [
        "點（餐）；訂購",
        "命令；指示",
        "順序",
        "訂單"
      ],
      "example_sentence": "I want to order a hamburger.",
      "translation": "我想點一個漢堡。",
      "pos": [
        "v",
        "n"
      ]
    },
    "paint": {
      "example_sentence": "I like to paint pictures.",
      "first_seen": "2026-03-29",
      "last_seen": "2026-03-29",
      "meanings": [
        "畫；塗；油漆"
      ],
      "translation": "我喜歡畫畫。"
    },
    "party": {
      "example_sentence": "We will have a party on Saturday.",
      "first_seen": "2026-03-26",
      "last_seen": "2026-03-26",
      "meanings": [
        "派對；聚會"
      ],
      "translation": "我們星期六要辦一個派對。"
    },
    "patience": {
      "first_seen": "2026-02-24",
      "last_seen": "2026-02-24",
      "meanings": [
        "耐心"
      ]
    },
    "picnic": {
      "example_sentence": "We will have a picnic in the park.",
      "first_seen": "2026-03-06",
      "last_seen": "2026-03-06",
      "meanings": [
        "野餐"
      ],
      "translation": "我們要在公園野餐。"
    },
    "pizza": {
      "example_sentence": "I want to eat pizza for dinner.",
      "first_seen": "2026-04-20",
      "last_seen": "2026-04-20",
      "meanings": [
        "披薩"
      ],
      "translation": "我晚餐想吃披薩。"
    },
    "place": {
      "example_sentence": "Please place your bag on the chair.",
      "first_seen": "2026-05-02",
      "last_seen": "2026-05-02",
      "meanings": [
        "地方；位置",
        "放置"
      ],
      "pos": [
        "n",
        "v"
      ],
      "translation": "請把你的書包放在椅子上。"
    },
    "player": {
      "example_sentence": "He is a good soccer player.",
      "first_seen": "2026-05-11",
      "last_seen": "2026-05-11",
      "meanings": [
        "（運動或遊戲的）選手",
        "玩家"
      ],
      "pos": "n",
      "translation": "他是一個很棒的足球選手。"
    },
    "pleasant": {
      "example_sentence": "It is a pleasant day today.",
      "first_seen": "2026-05-09",
      "last_seen": "2026-05-09",
      "meanings": [
        "愉快的；令人舒服的"
      ],
      "pos": "adj",
      "translation": "今天是個舒服的一天。"
    },
    "popular": {
      "example_sentence": "This song is popular with students.",
      "first_seen": "2026-04-13",
      "last_seen": "2026-04-13",
      "meanings": [
        "受歡迎的；流行的"
      ],
      "translation": "這首歌很受學生歡迎。"
    },
    "possible": {
      "example_sentence": "Is it possible to finish it today?",
      "first_seen": "2026-04-10",
      "last_seen": "2026-04-10",
      "meanings": [
        "可能的"
      ],
      "translation": "今天有可能把它完成嗎？"
    },
    "practice": {
      "example_sentence": "I practice English every day.",
      "first_seen": "2026-03-03",
      "last_seen": "2026-03-03",
      "meanings": [
        "練習"
      ],
      "translation": "我每天練習英文。"
    },
    "prepare": {
      "example_sentence": "I need to prepare for tomorrow's test.",
      "first_seen": "2026-02-28",
      "last_seen": "2026-02-28",
      "meanings": [
        "準備"
      ],
      "translation": "我需要為明天的考試做準備。"
    },
    "pretty": {
      "example_sentence": "That dress is pretty.",
      "first_seen": "2026-04-17",
      "last_seen": "2026-04-17",
      "meanings": [
        "漂亮的；可愛的"
      ],
      "translation": "那件洋裝很漂亮。"
    },
    "princess": {
      "example_sentence": "The princess lives in a castle.",
      "first_seen": "2026-04-08",
      "last_seen": "2026-04-08",
      "meanings": [
        "公主"
      ],
      "translation": "公主住在城堡裡。"
    },
    "probably": {
      "example_sentence": "It will probably rain tomorrow.",
      "first_seen": "2026-04-23",
      "last_seen": "2026-04-23",
      "meanings": [
        "大概；可能"
      ],
      "translation": "明天大概會下雨。"
    },
    "program": {
      "example_sentence": "I wrote a simple program for my class.",
      "first_seen": "2026-05-03",
      "last_seen": "2026-05-03",
      "meanings": [
        "程式；電腦程式",
        "（活動／課程的）方案；節目"
      ],
      "pos": [
        "n",
        "v"
      ],
      "translation": "我為課堂寫了一個簡單的程式。"
    },
    "promise": {
      "example_sentence": "I promise to finish my homework tonight.",
      "first_seen": "2026-03-06",
      "last_seen": "2026-03-06",
      "meanings": [
        "承諾；答應"
      ],
      "translation": "我答應今晚完成作業。"
    },
    "protect": {
      "example_sentence": "Trees help protect the earth.",
      "first_seen": "2026-03-02",
      "last_seen": "2026-03-02",
      "meanings": [
        "保護"
      ],
      "translation": "樹木有助於保護地球。"
    },
    "quiet": {
      "example_sentence": "Please be quiet in the library.",
      "first_seen": "2026-03-07",
      "last_seen": "2026-03-07",
      "meanings": [
        "安靜的"
      ],
      "translation": "在圖書館請安靜。"
    },
    "rainbow": {
      "example_sentence": "I can see a rainbow after the rain.",
      "first_seen": "2026-03-01",
      "last_seen": "2026-03-01",
      "meanings": [
        "彩虹"
      ],
      "translation": "下雨後我看見彩虹。"
    },
    "ready": {
      "example_sentence": "I am ready for the test.",
      "first_seen": "2026-03-22",
      "last_seen": "2026-03-22",
      "meanings": [
        "準備好的"
      ],
      "translation": "我已經準備好考試了。"
    },
    "real": {
      "example_sentence": "Is this story real?",
      "first_seen": "2026-04-21",
      "last_seen": "2026-04-21",
      "meanings": [
        "真的；真實的"
      ],
      "translation": "這個故事是真的嗎？"
    },
    "red": {
      "example_sentence": "The apple is red.",
      "first_seen": "2026-04-22",
      "last_seen": "2026-04-22",
      "meanings": [
        "紅色（的）"
      ],
      "translation": "這顆蘋果是紅色的。"
    },
    "repeat": {
      "example_sentence": "Please repeat after me.",
      "first_seen": "2026-05-10",
      "last_seen": "2026-05-10",
      "meanings": [
        "重複；再說一次"
      ],
      "pos": "v",
      "translation": "請跟我重複一次。"
    },
    "return": {
      "example_sentence": "Please return the book to the library tomorrow.",
      "first_seen": "2026-03-22",
      "last_seen": "2026-03-22",
      "meanings": [
        "回來；歸還"
      ],
      "translation": "請明天把這本書還到圖書館。"
    },
    "ride": {
      "example_sentence": "I ride my bike to school.",
      "first_seen": "2026-04-04",
      "last_seen": "2026-04-04",
      "meanings": [
        "騎（車/馬）；搭乘"
      ],
      "translation": "我騎腳踏車去上學。"
    },
    "ring": {
      "example_sentence": "She wears a ring on her finger.",
      "first_seen": "2026-05-06",
      "last_seen": "2026-05-06",
      "meanings": [
        "戒指"
      ],
      "pos": "n",
      "translation": "她手指上戴著一枚戒指。"
    },
    "rush": {
      "example_sentence": "Don't rush. We have enough time.",
      "first_seen": "2026-05-03",
      "last_seen": "2026-05-03",
      "meanings": [
        "匆忙；趕忙",
        "一陣忙亂；匆促"
      ],
      "pos": [
        "v",
        "n"
      ],
      "translation": "別急，我們時間很夠。"
    },
    "sand": {
      "example_sentence": "There is sand on the beach.",
      "first_seen": "2026-04-10",
      "last_seen": "2026-04-10",
      "meanings": [
        "沙子；沙"
      ],
      "translation": "海灘上有沙子。"
    },
    "say": {
      "example_sentence": "Please say it again.",
      "first_seen": "2026-04-29",
      "last_seen": "2026-04-29",
      "meanings": [
        "說；講"
      ],
      "pos": "v",
      "translation": "請再說一次。"
    },
    "send": {
      "example_sentence": "I will send a message to Dad.",
      "first_seen": "2026-05-12",
      "last_seen": "2026-05-12",
      "meanings": [
        "寄送；送出；派遣"
      ],
      "pos": "v",
      "translation": "我會傳一則訊息給爸爸。"
    },
    "share": {
      "first_seen": "2026-05-14",
      "last_seen": "2026-05-14",
      "meanings": [
        "分享；分擔；共用"
      ],
      "pos": "v",
      "example_sentence": "I want to share my snack with you.",
      "translation": "我想跟你分享我的點心。"
    },
    "shine": {
      "example_sentence": "The sun shines in the morning.",
      "first_seen": "2026-05-04",
      "last_seen": "2026-05-04",
      "meanings": [
        "發亮；照耀"
      ],
      "pos": "v",
      "translation": "太陽早上會發光。"
    },
    "side": {
      "example_sentence": "The ball rolled to the side of the road.",
      "first_seen": "2026-03-25",
      "last_seen": "2026-03-25",
      "meanings": [
        "旁邊；側面"
      ],
      "translation": "球滾到了路邊。"
    },
    "silly": {
      "example_sentence": "Don't be silly.",
      "first_seen": "2026-03-24",
      "last_seen": "2026-03-24",
      "meanings": [
        "傻傻的；笨笨的"
      ],
      "translation": "別傻傻的啦。"
    },
    "son": {
      "example_sentence": "My son plays basketball after school.",
      "first_seen": "2026-03-27",
      "last_seen": "2026-03-27",
      "meanings": [
        "兒子"
      ],
      "translation": "我兒子放學後打籃球。"
    },
    "sorry": {
      "example_sentence": "I'm sorry I'm late.",
      "first_seen": "2026-03-28",
      "last_seen": "2026-03-28",
      "meanings": [
        "對不起；抱歉"
      ],
      "translation": "對不起，我遲到了。"
    },
    "spider": {
      "example_sentence": "There is a spider on the wall.",
      "first_seen": "2026-04-05",
      "last_seen": "2026-04-05",
      "meanings": [
        "蜘蛛"
      ],
      "translation": "牆上有一隻蜘蛛。"
    },
    "spring": {
      "example_sentence": "Spring is my favorite season.",
      "first_seen": "2026-04-10",
      "last_seen": "2026-04-10",
      "meanings": [
        "春天"
      ],
      "translation": "春天是我最喜歡的季節。"
    },
    "store": {
      "example_sentence": "I went to the store with my dad.",
      "first_seen": "2026-05-01",
      "last_seen": "2026-05-01",
      "meanings": [
        "商店；店家"
      ],
      "pos": "n",
      "translation": "我跟爸爸一起去商店。"
    },
    "storm": {
      "example_sentence": "The storm is coming.",
      "first_seen": "2026-04-21",
      "last_seen": "2026-04-21",
      "meanings": [
        "暴風雨；風暴"
      ],
      "translation": "暴風雨要來了。"
    },
    "street": {
      "example_sentence": "Don't play on the street.",
      "first_seen": "2026-04-23",
      "last_seen": "2026-04-23",
      "meanings": [
        "街道；馬路"
      ],
      "translation": "不要在馬路上玩。"
    },
    "sugar": {
      "example_sentence": "Don't put too much sugar in your tea.",
      "first_seen": "2026-04-20",
      "last_seen": "2026-04-20",
      "meanings": [
        "糖"
      ],
      "translation": "你的茶不要加太多糖。"
    },
    "sunlight": {
      "example_sentence": "Plants need sunlight to grow.",
      "first_seen": "2026-03-05",
      "last_seen": "2026-03-05",
      "meanings": [
        "陽光"
      ],
      "translation": "植物需要陽光才能長大。"
    },
    "surely": {
      "example_sentence": "I will surely call you tonight.",
      "first_seen": "2026-05-08",
      "last_seen": "2026-05-08",
      "meanings": [
        "一定；肯定地"
      ],
      "pos": "adv",
      "translation": "我今晚一定會打給你。"
    },
    "sweet": {
      "example_sentence": "This cake is sweet.",
      "first_seen": "2026-04-15",
      "last_seen": "2026-04-15",
      "meanings": [
        "甜的；甜甜的"
      ],
      "translation": "這個蛋糕很甜。"
    },
    "teacher": {
      "example_sentence": "My teacher is kind and funny.",
      "first_seen": "2026-03-01",
      "last_seen": "2026-03-01",
      "meanings": [
        "老師"
      ],
      "translation": "我的老師很親切又有趣。"
    },
    "terrible": {
      "example_sentence": "The weather was terrible yesterday.",
      "first_seen": "2026-05-05",
      "last_seen": "2026-05-05",
      "meanings": [
        "糟糕的；可怕的"
      ],
      "pos": "adj",
      "translation": "昨天天氣很糟。"
    },
    "thick": {
      "example_sentence": "This book is thick.",
      "first_seen": "2026-05-11",
      "last_seen": "2026-05-11",
      "meanings": [
        "厚的",
        "濃的"
      ],
      "pos": "adj",
      "translation": "這本書很厚。"
    },
    "ticket": {
      "example_sentence": "I bought a ticket for the train.",
      "first_seen": "2026-03-23",
      "last_seen": "2026-03-23",
      "meanings": [
        "票"
      ],
      "translation": "我買了一張火車票。"
    },
    "together": {
      "example_sentence": "We can learn together after dinner.",
      "first_seen": "2026-03-02",
      "last_seen": "2026-03-02",
      "meanings": [
        "一起；共同"
      ],
      "translation": "晚餐後我們可以一起學習。"
    },
    "tomorrow": {
      "example_sentence": "We will have a test tomorrow.",
      "first_seen": "2026-04-02",
      "last_seen": "2026-04-02",
      "meanings": [
        "明天"
      ],
      "translation": "我們明天要考試。"
    },
    "top": {
      "example_sentence": "Put the book on top of the box.",
      "first_seen": "2026-05-06",
      "last_seen": "2026-05-06",
      "meanings": [
        "頂端；上面",
        "在…上面"
      ],
      "pos": [
        "n",
        "prep"
      ],
      "translation": "把書放在盒子上面。"
    },
    "treasure": {
      "first_seen": "2025-02-23",
      "last_seen": "2025-02-23",
      "meanings": [
        "寶藏"
      ]
    },
    "trip": {
      "example_sentence": "Our trip to the zoo was fun.",
      "first_seen": "2026-04-27",
      "last_seen": "2026-04-27",
      "meanings": [
        "旅行；出遊"
      ],
      "pos": "n",
      "translation": "我們去動物園的旅行很有趣。"
    },
    "typhoon": {
      "example_sentence": "A typhoon is coming.",
      "first_seen": "2026-04-11",
      "last_seen": "2026-04-11",
      "meanings": [
        "颱風"
      ],
      "translation": "颱風要來了。"
    },
    "ugly": {
      "example_sentence": "The ugly monster is not scary.",
      "first_seen": "2026-04-25",
      "last_seen": "2026-04-25",
      "meanings": [
        "醜的；難看的"
      ],
      "pos": "adj",
      "translation": "那隻醜醜的怪物並不可怕。"
    },
    "until": {
      "example_sentence": "Wait here until I come back.",
      "first_seen": "2026-05-09",
      "last_seen": "2026-05-09",
      "meanings": [
        "直到…為止"
      ],
      "pos": [
        "prep",
        "conj"
      ],
      "translation": "在這裡等我回來。"
    },
    "vegetable": {
      "example_sentence": "I eat vegetables every day.",
      "first_seen": "2026-03-28",
      "last_seen": "2026-03-28",
      "meanings": [
        "蔬菜"
      ],
      "translation": "我每天吃蔬菜。"
    },
    "very": {
      "example_sentence": "It is very cold today.",
      "first_seen": "2026-04-26",
      "last_seen": "2026-04-26",
      "meanings": [
        "非常；很"
      ],
      "pos": "adv",
      "translation": "今天很冷。"
    },
    "wait": {
      "example_sentence": "Please wait for me.",
      "first_seen": "2026-04-03",
      "last_seen": "2026-04-03",
      "meanings": [
        "等；等待"
      ],
      "translation": "請等我一下。"
    },
    "wear": {
      "example_sentence": "I wear my school uniform every day.",
      "first_seen": "2026-04-27",
      "last_seen": "2026-04-27",
      "meanings": [
        "穿；戴"
      ],
      "pos": "v",
      "translation": "我每天都穿校服。"
    },
    "weekend": {
      "example_sentence": "I visit my grandma on the weekend.",
      "first_seen": "2026-03-31",
      "last_seen": "2026-03-31",
      "meanings": [
        "週末"
      ],
      "translation": "我週末會去看外婆。"
    },
    "well": {
      "example_sentence": "She sings well.",
      "first_seen": "2026-04-27",
      "last_seen": "2026-04-27",
      "meanings": [
        "很好地；很不錯地"
      ],
      "pos": "adv",
      "translation": "她唱得很好。"
    },
    "whisper": {
      "example_sentence": "Please whisper in the library.",
      "first_seen": "2026-03-04",
      "last_seen": "2026-03-04",
      "meanings": [
        "小聲說；耳語"
      ],
      "translation": "在圖書館請小聲說話。"
    },
    "white": {
      "example_sentence": "My shoes are white.",
      "first_seen": "2026-04-26",
      "last_seen": "2026-04-26",
      "meanings": [
        "白色的；白的",
        "白色"
      ],
      "pos": [
        "adj",
        "n"
      ],
      "translation": "我的鞋子是白色的。"
    },
    "window": {
      "example_sentence": "The window is open.",
      "first_seen": "2026-04-30",
      "last_seen": "2026-04-30",
      "meanings": [
        "窗戶"
      ],
      "pos": "n",
      "translation": "窗戶是開著的。"
    },
    "woman": {
      "example_sentence": "The woman is a teacher.",
      "first_seen": "2026-03-29",
      "last_seen": "2026-03-29",
      "meanings": [
        "女人；女性"
      ],
      "translation": "那位女士是老師。"
    },
    "yellow": {
      "example_sentence": "I have a yellow raincoat.",
      "first_seen": "2026-03-31",
      "last_seen": "2026-03-31",
      "meanings": [
        "黃色（的）"
      ],
      "translation": "我有一件黃色的雨衣。"
    }
  }
}
